hlm2_music_changer/__init__.py
hlm2_music_changer/dirtools.py
hlm2_music_changer/hlm2mc.py
hlm2_music_changer-1.0.1.dist-info/entry_points.txt
hlm2_music_changer-1.0.1.dist-info/LICENSE
hlm2_music_changer-1.0.1.dist-info/WHEEL
hlm2_music_changer-1.0.1.dist-info/METADATA
hlm2_music_changer-1.0.1.dist-info/RECORD
