Metadata-Version: 2.1
Name: hlm2-music-changer
Version: 1.0.1
Summary: A Python module to make the installation and management of Hotline Miami 2 music mods simpler.
License: MIT
Author: generic-user1
Author-email: 89677116+generic-user1@users.noreply.github.com
Requires-Python: >=3.9,<4.0
Classifier: License :: OSI Approved :: MIT License
Classifier: Programming Language :: Python :: 3
Classifier: Programming Language :: Python :: 3.10
Classifier: Programming Language :: Python :: 3.9
Requires-Dist: appdirs (>=1.4.4,<2.0.0)
